win10toast/__init__.py
win10toast/__main__.py
win10toast/data/python.ico
win10toast-0.8.dist-info/DESCRIPTION.rst
win10toast-0.8.dist-info/METADATA
win10toast-0.8.dist-info/RECORD
win10toast-0.8.dist-info/WHEEL
win10toast-0.8.dist-info/metadata.json
win10toast-0.8.dist-info/top_level.txt
