Metadata-Version: 2.0
Name: win10toast
Version: 0.8
Summary: An easy-to-use Python library for displaying Windows 10 Toast Notifications
Home-page: https://github.com/jithurjacob/Windows-10-Toast-Notifications
Author: Jithu R Jacob
Author-email: jithurjacob@gmail.com
License: BSD
Download-URL: https://github.com/jithurjacob/Windows-10-Toast-Notifications/tarball/0.4
Platform: UNKNOWN
Classifier: Development Status :: 3 - Alpha
Classifier: Topic :: Utilities
Classifier: Operating System :: Microsoft
Classifier: Environment :: Win32 (MS Windows)
Classifier: License :: OSI Approved :: BSD License
Requires-Dist: pypiwin32
Requires-Dist: setuptools
